LICENSE
MANIFEST.in
README.md
requirements.txt
setup.py
aioslack/__init__.py
aioslack/core.py
aioslack/state.py
aioslack/types.py
aioslack.egg-info/PKG-INFO
aioslack.egg-info/SOURCES.txt
aioslack.egg-info/dependency_links.txt
aioslack.egg-info/requires.txt
aioslack.egg-info/top_level.txt