Metadata-Version: 2.1
Name: aioslack
Version: 0.4.0
Summary: asyncio slack api
Home-page: https://github.com/jreese/aioslack
Author: John Reese
Author-email: john@noswap.com
License: MIT
Platform: UNKNOWN
Classifier: Development Status :: 3 - Alpha
Classifier: Framework :: AsyncIO
Classifier: Intended Audience :: Developers
Classifier: License :: OSI Approved :: MIT License
Classifier: Programming Language :: Python
Classifier: Programming Language :: Python :: 3
Classifier: Programming Language :: Python :: 3.6
Classifier: Topic :: Software Development :: Libraries
